{
  "title": "Hot Sauce Must Be HOT! #funfact",
  "id": "o4XRpgyz2O8",
  "description": "A supplier once told David Tran the creator Sriracha hot sauce that it was too spicy and suggested he add a tomato base to make it sweeter. David replied \"hot sauce must be hot! If you don’t like it hot, use less. We don’t make mayonnaise here.\"",
  "publishedAt": "2023-06-13T19:00:28Z",
  "thumbnails": "https://i.ytimg.com/vi/o4XRpgyz2O8/sddefault.jpg",
  "channelTitle": "Doug Sharpe",
  "tags": [
    "hot sauce",
    "sriracha",
    "sriracha sauce",
    "david tran",
    "rooster brand",
    "interesting facts",
    "amazing facts",
    "cool facts",
    "fun facts",
    "random facts",
    "first we feast",
    "first we feast hot ones",
    "interesting facts shorts",
    "interesting facts channel",
    "amazing facts short video",
    "fun facts shorts",
    "amazing facts tv",
    "amazing facts about the world",
    "interesting facts about the world",
    "fun facts about the world",
    "random facts about the world",
    "random facts tiktok",
    "random facts shorts",
    "cool facts shorts"
  ]
}
